{"total": 10, "accepted": 8, "utilization": 0.79, "SFCs": {"0": {"nodes": ["8", "1", "2", "3", "0", "3", "9", "17", "23", "29", "35", "36", "40", "46", "50", "52", "55", "58", "60", "62", "67", "74", "71", "81", "80", "69", "64"], "VNFs": [4]}, "1": {"nodes": ["30", "37", "40", "46", "49", "56", "75", "78", "66", "68", "63", "67", "74", "83", "84", "82", "81", "80", "69", "79", "86", "93"], "VNFs": [14, 18]}, "2": {"nodes": ["59", "57", "54", "65", "62", "65", "45", "34", "48"], "VNFs": [4]}, "3": {"nodes": ["88", "84", "82", "81", "71", "74", "83", "85", "101", "102", "98", "94", "100", "99", "97", "96", "95"], "VNFs": [3, 8]}, "5": {"nodes": ["99", "100", "94", "87", "85", "83", "84", "82", "81", "80", "69", "79", "69", "64", "59"], "VNFs": [2, 11]}, "7": {"nodes": ["96", "97", "99", "100", "94", "87", "85", "83", "74", "67", "62", "60", "58", "55", "52", "50", "46", "40", "41", "33", "20", "15", "10", "16", "24"], "VNFs": [4]}, "8": {"nodes": ["90", "87", "85", "83", "84", "82", "81", "71", "74", "67", "62", "65", "45", "34"], "VNFs": [2, 6]}, "9": {"nodes": ["37", "40", "36", "35", "29", "23", "17", "9", "3", "9", "17", "23", "29", "35", "36", "40", "37", "30"], "VNFs": [8]}}, "time": 5.578125}