{"total": 10, "accepted": 6, "utilization": 0.93, "SFCs": {"1": {"nodes": ["4", "5", "9", "8", "11", "12", "13", "10", "3", "4", "6", "7", "8"], "VNFs": [2, 6, 10]}, "2": {"nodes": ["10", "3", "4", "6", "4", "3", "10", "13", "12", "5"], "VNFs": [3, 7]}, "3": {"nodes": ["4", "5", "12", "13", "8", "11", "10", "3", "1"], "VNFs": [2]}, "5": {"nodes": ["10", "13", "12", "11", "8", "9", "5"], "VNFs": [5, 5]}, "7": {"nodes": ["7", "0", "2", "5", "12", "11", "10"], "VNFs": [4]}, "9": {"nodes": ["5", "9", "8", "11", "8"], "VNFs": [3]}}, "time": 1.8125}