{"total": 20, "accepted": 9, "utilization": 0.37, "SFCs": {"3": {"nodes": ["73", "74", "70", "64", "65", "54", "46", "41", "40", "39", "33", "30", "24", "20", "17", "14"], "VNFs": [9]}, "4": {"nodes": ["54", "62", "61", "59", "56", "40", "32", "28", "25", "18", "13", "3", "5"], "VNFs": [4, 9]}, "9": {"nodes": ["71", "69", "68", "65", "54", "46", "41", "40", "39", "33", "30", "24", "30", "33", "39", "40", "41", "46", "48"], "VNFs": [11, 11]}, "10": {"nodes": ["42", "38", "34", "31", "27", "24", "16", "11", "16", "18", "13", "3", "1"], "VNFs": [7, 9]}, "11": {"nodes": ["5", "3", "13", "18", "25", "28", "32", "40", "56", "59"], "VNFs": [4]}, "13": {"nodes": ["23", "24", "16", "11", "6", "3", "5", "0", "5"], "VNFs": [7]}, "16": {"nodes": ["51", "56", "40", "32", "28", "25", "18", "15", "18", "13", "11", "16", "17", "14"], "VNFs": [7]}, "17": {"nodes": ["42", "38", "39", "33", "30", "24", "16", "18", "25", "28", "32", "40", "56", "58", "55"], "VNFs": [2, 7]}, "19": {"nodes": ["72", "71", "69", "68", "65", "54", "46", "41", "40", "32", "28", "25", "28", "32", "40", "41", "61", "62", "66"], "VNFs": [9, 11, 11]}}, "time": 9.125}