{"total": 10, "accepted": 8, "utilization": 0.7, "SFCs": {"0": {"nodes": ["8", "6", "3", "5", "0", "2"], "VNFs": [2]}, "1": {"nodes": ["10", "12", "11", "6", "3", "13", "11", "12", "14"], "VNFs": [2, 4, 4]}, "2": {"nodes": ["5", "3", "13", "18", "16", "24", "30", "33"], "VNFs": [3]}, "4": {"nodes": ["59", "61", "62", "66", "63", "58", "55", "49", "42", "38", "34", "31", "27", "22"], "VNFs": [2, 6]}, "5": {"nodes": ["2", "9", "15", "18", "16", "11", "16", "24", "30", "33"], "VNFs": [5]}, "6": {"nodes": ["73", "74", "70", "64", "65", "54", "62", "61", "41", "40", "32", "28", "25", "18", "13", "3", "5", "0", "13", "18", "25", "28", "32", "40", "56", "58", "55", "58"], "VNFs": [15, 17, 26]}, "7": {"nodes": ["56", "51", "42", "38", "39", "33", "30", "24", "16", "11", "6", "8"], "VNFs": [6]}, "9": {"nodes": ["65", "54", "62", "61", "41", "40", "32", "28", "25", "18", "13", "11", "13", "3", "1"], "VNFs": [1, 11]}}, "time": 5.015625}